{
  "lookup": {
    "rules": {
      "[{\"prev_action\": {\"action_name\": \"action_listen\"}, \"user\": {\"intent\": \"client\"}}]": "client_form",
      "[{\"prev_action\": {\"action_name\": \"action_listen\"}, \"user\": {\"intent\": \"client\"}}, {\"active_loop\": {\"name\": \"client_form\"}, \"prev_action\": {\"action_name\": \"client_form\"}, \"user\": {\"intent\": \"client\"}}]": "action_listen",
      "[{\"prev_action\": {\"action_name\": \"action_listen\"}, \"user\": {\"intent\": \"greet\"}}]": "utter_greet",
      "[{\"prev_action\": {\"action_name\": \"action_listen\"}, \"user\": {\"intent\": \"greet\"}}, {\"prev_action\": {\"action_name\": \"utter_greet\"}, \"user\": {\"intent\": \"greet\"}}]": "utter_question_statut",
      "[{\"prev_action\": {\"action_name\": \"action_listen\"}, \"user\": {\"intent\": \"greet\"}}, {\"prev_action\": {\"action_name\": \"utter_greet\"}, \"user\": {\"intent\": \"greet\"}}, {\"prev_action\": {\"action_name\": \"utter_question_statut\"}, \"user\": {\"intent\": \"greet\"}}]": "action_listen",
      "[{\"prev_action\": {\"action_name\": \"action_listen\"}, \"user\": {\"intent\": \"partenaire\"}}]": "utter_partenaire",
      "[{\"prev_action\": {\"action_name\": \"action_listen\"}, \"user\": {\"intent\": \"partenaire\"}}, {\"prev_action\": {\"action_name\": \"utter_partenaire\"}, \"user\": {\"intent\": \"partenaire\"}}]": "action_listen",
      "[{\"prev_action\": {\"action_name\": \"action_listen\"}, \"user\": {\"intent\": \"recruteur\"}}]": "utter_recruteur",
      "[{\"prev_action\": {\"action_name\": \"action_listen\"}, \"user\": {\"intent\": \"recruteur\"}}, {\"prev_action\": {\"action_name\": \"utter_recruteur\"}, \"user\": {\"intent\": \"recruteur\"}}]": "action_listen",
      "[{\"prev_action\": {\"action_name\": \"action_listen\"}, \"user\": {\"intent\": \"thanks\"}}]": "utter_thanks",
      "[{\"prev_action\": {\"action_name\": \"action_listen\"}, \"user\": {\"intent\": \"thanks\"}}, {\"prev_action\": {\"action_name\": \"utter_thanks\"}, \"user\": {\"intent\": \"thanks\"}}]": "action_listen",
      "[{\"prev_action\": {\"action_name\": \"action_listen\"}, \"user\": {\"intent\": \"condidat\"}}]": "utter_condidat",
      "[{\"prev_action\": {\"action_name\": \"action_listen\"}, \"user\": {\"intent\": \"condidat\"}}, {\"prev_action\": {\"action_name\": \"utter_condidat\"}, \"user\": {\"intent\": \"condidat\"}}]": "action_listen",
      "[{\"active_loop\": {\"name\": \"should_not_be_set\"}, \"prev_action\": {\"action_name\": \"client_form\"}}]": "utter_submit",
      "[{\"active_loop\": {\"name\": \"should_not_be_set\"}, \"prev_action\": {\"action_name\": \"client_form\"}}, {\"active_loop\": {\"name\": \"should_not_be_set\"}, \"prev_action\": {\"action_name\": \"utter_submit\"}}]": "action_listen",
      "[{\"prev_action\": {\"action_name\": \"action_listen\"}, \"user\": {\"intent\": \"goodbye\"}}]": "utter_goodbye",
      "[{\"prev_action\": {\"action_name\": \"action_listen\"}, \"user\": {\"intent\": \"goodbye\"}}, {\"prev_action\": {\"action_name\": \"utter_goodbye\"}, \"user\": {\"intent\": \"goodbye\"}}]": "action_listen",
      "[{\"prev_action\": {\"action_name\": \"action_listen\"}, \"user\": {\"intent\": \"bot_challenge\"}}]": "utter_iamabot",
      "[{\"prev_action\": {\"action_name\": \"action_listen\"}, \"user\": {\"intent\": \"bot_challenge\"}}, {\"prev_action\": {\"action_name\": \"utter_iamabot\"}, \"user\": {\"intent\": \"bot_challenge\"}}]": "action_listen"
    },
    "rule_only_slots": [],
    "rule_only_loops": [
      "client_form"
    ],
    "rules_for_loop_unhappy_path": {
      "[{\"prev_action\": {\"action_name\": \"action_listen\"}}, {\"active_loop\": {\"name\": \"client_form\"}, \"prev_action\": {\"action_name\": \"client_form\"}, \"user\": {\"intent\": \"client\"}}]": "do_not_predict_loop_action"
    },
    "rules_not_in_stories": [
      "[{\"prev_action\": {\"action_name\": \"action_listen\"}, \"user\": {\"intent\": \"bot_challenge\"}}]",
      "[{\"prev_action\": {\"action_name\": \"action_listen\"}, \"user\": {\"intent\": \"greet\"}}]",
      "[{\"prev_action\": {\"action_name\": \"action_listen\"}, \"user\": {\"intent\": \"goodbye\"}}, {\"prev_action\": {\"action_name\": \"utter_goodbye\"}, \"user\": {\"intent\": \"goodbye\"}}]",
      "[{\"prev_action\": {\"action_name\": \"action_listen\"}, \"user\": {\"intent\": \"greet\"}}, {\"prev_action\": {\"action_name\": \"utter_greet\"}, \"user\": {\"intent\": \"greet\"}}]",
      "[{\"prev_action\": {\"action_name\": \"action_listen\"}, \"user\": {\"intent\": \"partenaire\"}}]",
      "[{\"prev_action\": {\"action_name\": \"action_listen\"}, \"user\": {\"intent\": \"goodbye\"}}]",
      "[{\"prev_action\": {\"action_name\": \"action_listen\"}, \"user\": {\"intent\": \"thanks\"}}, {\"prev_action\": {\"action_name\": \"utter_thanks\"}, \"user\": {\"intent\": \"thanks\"}}]",
      "predicting default action with intent session_start",
      "[{\"prev_action\": {\"action_name\": \"action_listen\"}, \"user\": {\"intent\": \"partenaire\"}}, {\"prev_action\": {\"action_name\": \"utter_partenaire\"}, \"user\": {\"intent\": \"partenaire\"}}]",
      "[{\"prev_action\": {\"action_name\": \"action_listen\"}, \"user\": {\"intent\": \"bot_challenge\"}}, {\"prev_action\": {\"action_name\": \"utter_iamabot\"}, \"user\": {\"intent\": \"bot_challenge\"}}]",
      "predicting default action with intent restart",
      "[{\"prev_action\": {\"action_name\": \"action_listen\"}, \"user\": {\"intent\": \"condidat\"}}]",
      "[{\"prev_action\": {\"action_name\": \"action_listen\"}, \"user\": {\"intent\": \"thanks\"}}]",
      "[{\"prev_action\": {\"action_name\": \"action_listen\"}, \"user\": {\"intent\": \"greet\"}}, {\"prev_action\": {\"action_name\": \"utter_greet\"}, \"user\": {\"intent\": \"greet\"}}, {\"prev_action\": {\"action_name\": \"utter_question_statut\"}, \"user\": {\"intent\": \"greet\"}}]",
      "[{\"prev_action\": {\"action_name\": \"action_listen\"}, \"user\": {\"intent\": \"recruteur\"}}, {\"prev_action\": {\"action_name\": \"utter_recruteur\"}, \"user\": {\"intent\": \"recruteur\"}}]",
      "[{\"prev_action\": {\"action_name\": \"action_listen\"}, \"user\": {\"intent\": \"recruteur\"}}]",
      "[{\"prev_action\": {\"action_name\": \"action_listen\"}, \"user\": {\"intent\": \"condidat\"}}, {\"prev_action\": {\"action_name\": \"utter_condidat\"}, \"user\": {\"intent\": \"condidat\"}}]",
      "handling active loops and forms - client_form - action_listen",
      "handling active loops and forms - client_form",
      "predicting default action with intent back"
    ]
  }
}